modelresolvers/__init__.py
modelresolvers/modelresolvers.py
modelresolvers/schema.py
modelresolvers-0.2.2.dist-info/LICENSE
modelresolvers-0.2.2.dist-info/METADATA
modelresolvers-0.2.2.dist-info/WHEEL
modelresolvers-0.2.2.dist-info/RECORD
